meshtastic_mqtt_json/__init__.py
meshtastic_mqtt_json/client.py
meshtastic_mqtt_json-2.0.0.dist-info/licenses/LICENSE
meshtastic_mqtt_json-2.0.0.dist-info/METADATA
meshtastic_mqtt_json-2.0.0.dist-info/WHEEL
meshtastic_mqtt_json-2.0.0.dist-info/entry_points.txt
meshtastic_mqtt_json-2.0.0.dist-info/top_level.txt
meshtastic_mqtt_json-2.0.0.dist-info/RECORD
