Metadata-Version: 2.4
Name: meshtastic-mqtt-json
Version: 2.0.0
Summary: A lightweight Python library for parsing Meshtastic MQTT messages
Home-page: https://github.com/acidvegas/meshtastic_mqtt_json
Author: acidvegas
Author-email: acid.vegas@acid.vegas
Project-URL: Bug Tracker, https://github.com/acidvegas/meshtastic_mqtt_json/issues
Project-URL: Documentation, https://github.com/acidvegas/meshtastic_mqtt_json#readme
Project-URL: Source Code, https://github.com/acidvegas/meshtastic_mqtt_json
Classifier: Development Status :: 3 - Alpha
Classifier: Intended Audience :: Developers
Classifier: License :: OSI Approved :: ISC License (ISCL)
Classifier: Operating System :: OS Independent
Classifier: Programming Language :: Python :: 3
Classifier: Programming Language :: Python :: 3.6
Classifier: Programming Language :: Python :: 3.7
Classifier: Programming Language :: Python :: 3.8
Classifier: Programming Language :: Python :: 3.9
Classifier: Topic :: Communications
Requires-Python: >=3.6
License-File: LICENSE
Requires-Dist: cryptography
Requires-Dist: protobuf
Requires-Dist: meshtastic
Requires-Dist: paho-mqtt
Dynamic: author
Dynamic: author-email
Dynamic: classifier
Dynamic: description
Dynamic: description-content-type
Dynamic: home-page
Dynamic: license-file
Dynamic: project-url
Dynamic: requires-dist
Dynamic: requires-python
Dynamic: summary
